Workbook
Name Slicer_order_date__Month: #N/A
Name Slicer_order_status: #N/A
Name Slicer_payment_method: #N/A

Sheet Customers
A1: customer_id | B1: customer_name | C1: city | D1: state | E1: signup_date
A2: 1 | B2: Amit Sharma | C2: Mumbai | D2: Maharashtra | E2: 44941
A3: 2 | B3: Priya Patel | C3: Pune | D3: Maharashtra | E3: 44977
A4: 3 | B4: Rahul Verma | C4: Delhi | D4: Delhi | E4: 44995
A5: 4 | B5: Sneha Joshi | C5: Nagpur | D5: Maharashtra | E5: 45021
A6: 5 | B6: Vikram Singh | C6: Bangalore | D6: Karnataka | E6: 45064
A7: 6 | B7: Neha Gupta | C7: Hyderabad | D7: Telangana | E7: 45089
A8: 7 | B8: Arjun Mehta | C8: Mumbai | D8: Maharashtra | E8: 45132
A9: 8 | B9: Kavya Rao | C9: Chennai | D9: Tamil Nadu | E9: 45152
A10: 9 | B10: Rohan Das | C10: Kolkata | D10: West Bengal | E10: 45172
A11: 10 | B11: Pooja Shah | C11: Ahmedabad | D11: Gujarat | E11: 45220

Sheet Orders
A1: order_id | B1: customer_id | C1: order_date | D1: order_status | E1: City
A2: 1001 | B2: 1 | C2: 45296 | D2: Delivered | E2: =_xlfn.XLOOKUP(Orders[[#This Row],[customer_id]],'Customers'!A:A,'Customers'!C:C,"Not Found") -> Mumbai
A3: 1002 | B3: 2 | C3: 45299 | D3: Delivered | E3: =_xlfn.XLOOKUP(Orders[[#This Row],[customer_id]],'Customers'!A:A,'Customers'!C:C,"Not Found") -> Pune
A4: 1003 | B4: 3 | C4: 45303 | D4: Cancelled | E4: =_xlfn.XLOOKUP(Orders[[#This Row],[customer_id]],'Customers'!A:A,'Customers'!C:C,"Not Found") -> Delhi
A5: 1004 | B5: 4 | C5: 45324 | D5: Delivered | E5: =_xlfn.XLOOKUP(Orders[[#This Row],[customer_id]],'Customers'!A:A,'Customers'!C:C,"Not Found") -> Nagpur
A6: 1005 | B6: 5 | C6: 45332 | D6: Delivered | E6: =_xlfn.XLOOKUP(Orders[[#This Row],[customer_id]],'Customers'!A:A,'Customers'!C:C,"Not Found") -> Bangalore
A7: 1006 | B7: 1 | C7: 45337 | D7: Delivered | E7: =_xlfn.XLOOKUP(Orders[[#This Row],[customer_id]],'Customers'!A:A,'Customers'!C:C,"Not Found") -> Mumbai
A8: 1007 | B8: 6 | C8: 45352 | D8: Pending | E8: =_xlfn.XLOOKUP(Orders[[#This Row],[customer_id]],'Customers'!A:A,'Customers'!C:C,"Not Found") -> Hyderabad
A9: 1008 | B9: 7 | C9: 45358 | D9: Delivered | E9: =_xlfn.XLOOKUP(Orders[[#This Row],[customer_id]],'Customers'!A:A,'Customers'!C:C,"Not Found") -> Mumbai
A10: 1009 | B10: 8 | C10: 45366 | D10: Delivered | E10: =_xlfn.XLOOKUP(Orders[[#This Row],[customer_id]],'Customers'!A:A,'Customers'!C:C,"Not Found") -> Chennai
A11: 1010 | B11: 9 | C11: 45371 | D11: Delivered | E11: =_xlfn.XLOOKUP(Orders[[#This Row],[customer_id]],'Customers'!A:A,'Customers'!C:C,"Not Found") -> Kolkata
A12: 1011 | B12: 10 | C12: 45387 | D12: Delivered | E12: =_xlfn.XLOOKUP(Orders[[#This Row],[customer_id]],'Customers'!A:A,'Customers'!C:C,"Not Found") -> Ahmedabad
A13: 1012 | B13: 3 | C13: 45392 | D13: Delivered | E13: =_xlfn.XLOOKUP(Orders[[#This Row],[customer_id]],'Customers'!A:A,'Customers'!C:C,"Not Found") -> Delhi
... A16: 1015 | B16: 7 | C16: 45427 | D16: Delivered | E16: =_xlfn.XLOOKUP(Orders[[#This Row],[customer_id]],'Customers'!A:A,'Customers'!C:C,"Not Found") -> Mumbai

Sheet Order details
A1: order_detail_id | B1: order_id | C1: product_id | D1: quantity | E1: Revenue | F1: Category | G1: Product Name
A2: 1 | B2: 1001 | C2: 101 | D2: 1 | E2: =D2*_xlfn.XLOOKUP(C2,Products[product_id],Products[price]) -> 55000 | F2: =_xlfn.XLOOKUP(Order_details[[#This Row],[product_id]],Products!A:A,Products!C:C) -> Electronics | G2: =_xlfn.XLOOKUP(Order_details[[#This Row],[product_id]],Products!A:A,Products!B:B) -> Laptop
A3: 8 | B3: 1005 | C3: 101 | D3: 1 | E3: =D3*_xlfn.XLOOKUP(C3,Products[product_id],Products[price]) -> 55000 | F3: =_xlfn.XLOOKUP(Order_details[[#This Row],[product_id]],Products!A:A,Products!C:C) -> Electronics | G3: =_xlfn.XLOOKUP(Order_details[[#This Row],[product_id]],Products!A:A,Products!B:B) -> Laptop
A4: 15 | B4: 1009 | C4: 101 | D4: 1 | E4: =D4*_xlfn.XLOOKUP(C4,Products[product_id],Products[price]) -> 55000 | F4: =_xlfn.XLOOKUP(Order_details[[#This Row],[product_id]],Products!A:A,Products!C:C) -> Electronics | G4: =_xlfn.XLOOKUP(Order_details[[#This Row],[product_id]],Products!A:A,Products!B:B) -> Laptop
A5: 23 | B5: 1014 | C5: 101 | D5: 1 | E5: =D5*_xlfn.XLOOKUP(C5,Products[product_id],Products[price]) -> 55000 | F5: =_xlfn.XLOOKUP(Order_details[[#This Row],[product_id]],Products!A:A,Products!C:C) -> Electronics | G5: =_xlfn.XLOOKUP(Order_details[[#This Row],[product_id]],Products!A:A,Products!B:B) -> Laptop
A6: 3 | B6: 1002 | C6: 102 | D6: 1 | E6: =D6*_xlfn.XLOOKUP(C6,Products[product_id],Products[price]) -> 30000 | F6: =_xlfn.XLOOKUP(Order_details[[#This Row],[product_id]],Products!A:A,Products!C:C) -> Electronics | G6: =_xlfn.XLOOKUP(Order_details[[#This Row],[product_id]],Products!A:A,Products!B:B) -> Smartphone
A7: 10 | B7: 1006 | C7: 102 | D7: 1 | E7: =D7*_xlfn.XLOOKUP(C7,Products[product_id],Products[price]) -> 30000 | F7: =_xlfn.XLOOKUP(Order_details[[#This Row],[product_id]],Products!A:A,Products!C:C) -> Electronics | G7: =_xlfn.XLOOKUP(Order_details[[#This Row],[product_id]],Products!A:A,Products!B:B) -> Smartphone
A8: 19 | B8: 1011 | C8: 102 | D8: 2 | E8: =D8*_xlfn.XLOOKUP(C8,Products[product_id],Products[price]) -> 60000 | F8: =_xlfn.XLOOKUP(Order_details[[#This Row],[product_id]],Products!A:A,Products!C:C) -> Electronics | G8: =_xlfn.XLOOKUP(Order_details[[#This Row],[product_id]],Products!A:A,Products!B:B) -> Smartphone
A9: 25 | B9: 1015 | C9: 102 | D9: 1 | E9: =D9*_xlfn.XLOOKUP(C9,Products[product_id],Products[price]) -> 30000 | F9: =_xlfn.XLOOKUP(Order_details[[#This Row],[product_id]],Products!A:A,Products!C:C) -> Electronics | G9: =_xlfn.XLOOKUP(Order_details[[#This Row],[product_id]],Products!A:A,Products!B:B) -> Smartphone
A10: 2 | B10: 1001 | C10: 103 | D10: 2 | E10: =D10*_xlfn.XLOOKUP(C10,Products[product_id],Products[price]) -> 5000 | F10: =_xlfn.XLOOKUP(Order_details[[#This Row],[product_id]],Products!A:A,Products!C:C) -> Electronics | G10: =_xlfn.XLOOKUP(Order_details[[#This Row],[product_id]],Products!A:A,Products!B:B) -> Headphones
A11: 11 | B11: 1006 | C11: 103 | D11: 1 | E11: =D11*_xlfn.XLOOKUP(C11,Products[product_id],Products[price]) -> 2500 | F11: =_xlfn.XLOOKUP(Order_details[[#This Row],[product_id]],Products!A:A,Products!C:C) -> Electronics | G11: =_xlfn.XLOOKUP(Order_details[[#This Row],[product_id]],Products!A:A,Products!B:B) -> Headphones
A12: 20 | B12: 1012 | C12: 103 | D12: 2 | E12: =D12*_xlfn.XLOOKUP(C12,Products[product_id],Products[price]) -> 5000 | F12: =_xlfn.XLOOKUP(Order_details[[#This Row],[product_id]],Products!A:A,Products!C:C) -> Electronics | G12: =_xlfn.XLOOKUP(Order_details[[#This Row],[product_id]],Products!A:A,Products!B:B) -> Headphones
A13: 5 | B13: 1003 | C13: 104 | D13: 1 | E13: =D13*_xlfn.XLOOKUP(C13,Products[product_id],Products[price]) -> 8500 | F13: =_xlfn.XLOOKUP(Order_details[[#This Row],[product_id]],Products!A:A,Products!C:C) -> Furniture | G13: =_xlfn.XLOOKUP(Order_details[[#This Row],[product_id]],Products!A:A,Products!B:B) -> Office Chair
... A27: 21 | B27: 1012 | C27: 110 | D27: 5 | E27: =D27*_xlfn.XLOOKUP(C27,Products[product_id],Products[price]) -> 1250 | F27: =_xlfn.XLOOKUP(Order_details[[#This Row],[product_id]],Products!A:A,Products!C:C) -> Stationery | G27: =_xlfn.XLOOKUP(Order_details[[#This Row],[product_id]],Products!A:A,Products!B:B) -> Notebook

Sheet Payments
A1: payment_id | B1: order_id | C1: payment_date | D1: payment_method | E1: amount | F1: payment_status
A2: 501 | B2: 1001 | C2: 45296 | D2: Credit Card | E2: 60000 | F2: Paid
A3: 502 | B3: 1002 | C3: 45299 | D3: UPI | E3: 31500 | F3: Paid
A4: 503 | B4: 1003 | C4: 45303 | D4: Credit Card | E4: 8500 | F4: Refunded
A5: 504 | B5: 1004 | C5: 45324 | D5: Debit Card | E5: 15600 | F5: Paid
A6: 505 | B6: 1005 | C6: 45332 | D6: UPI | E6: 56600 | F6: Paid
A7: 506 | B7: 1006 | C7: 45337 | D7: Credit Card | E7: 32500 | F7: Paid
A8: 507 | B8: 1007 | C8: 45352 | D8: UPI | E8: 8500 | F8: Pending
A9: 508 | B9: 1008 | C9: 45358 | D9: Cash | E9: 6900 | F9: Paid
A10: 509 | B10: 1009 | C10: 45366 | D10: Credit Card | E10: 55800 | F10: Paid
A11: 510 | B11: 1010 | C11: 45371 | D11: UPI | E11: 13200 | F11: Paid
A12: 511 | B12: 1011 | C12: 45387 | D12: Credit Card | E12: 60000 | F12: Paid
A13: 512 | B13: 1012 | C13: 45392 | D13: Debit Card | E13: 5500 | F13: Paid
... A16: 515 | B16: 1015 | C16: 45427 | D16: UPI | E16: 31800 | F16: Paid

Sheet Products
A1: product_id | B1: product_name | C1: category | D1: price
A2: 101 | B2: Laptop | C2: Electronics | D2: 55000
A3: 102 | B3: Smartphone | C3: Electronics | D3: 30000
A4: 103 | B4: Headphones | C4: Electronics | D4: 2500
A5: 104 | B5: Office Chair | C5: Furniture | D5: 8500
A6: 105 | B6: Desk | C6: Furniture | D6: 12000
A7: 106 | B7: Backpack | C7: Accessories | D7: 1800
A8: 107 | B8: Keyboard | C8: Electronics | D8: 1500
A9: 108 | B9: Mouse | C9: Electronics | D9: 800
A10: 109 | B10: Water Bottle | C10: Lifestyle | D10: 600
A11: 110 | B11: Notebook | C11: Stationery | D11: 250

Sheet Dashboard
A2: RETAIL SALES ANALYSIS DASHBOARD

Sheet Analysis
A1: Distinct Count of customer_id | B1: Sum of Revenue | C1: Count of order_id | D1: Sum of quantity | E1: Avg order Vlaue
A2: 10 | B2: 453650 | C2: 15 | D2: 41 | E2: =GETPIVOTDATA("[Measures].[Sum of Revenue]",$B$1)/GETPIVOTDATA("[Measures].[Count of order_id]",$C$1) -> 30243.333
G4: Row Labels | H4: Sum of Revenue
A5: order_date (Year) | B5: order_date (Month) | C5: Count of order_id | G5: Desk | H5: 24000
A6: 2024 | B6: Jan | C6: 3 | G6: Headphones | H6: 12500
A7: 2024 | B7: Feb | C7: 3 | G7: Laptop | H7: 220000
A8: 2024 | B8: Mar | C8: 4 | G8: Office Chair | H8: 25500
A9: 2024 | B9: Apr | C9: 3 | G9: Smartphone | H9: 150000
A10: 2024 | B10: May | C10: 2 | G10: Grand Total | H10: 432000
A11: Grand Total | C11: 15
F28: Row Labels | G28: Count of order_id
A29: Row Labels | B29: Sum of Revenue | F29: Ahmedabad | G29: 1
A30: Accessories | B30: 9000 | F30: Bangalore | G30: 2
A31: Electronics | B31: 390900 | F31: Chennai | G31: 1
A32: Furniture | B32: 49500 | F32: Delhi | G32: 2
A33: Lifestyle | B33: 3000 | F33: Hyderabad | G33: 1
A34: Stationery | B34: 1250 | F34: Kolkata | G34: 1
A35: Grand Total | B35: 453650 | F35: Mumbai | G35: 4
F36: Nagpur | G36: 2
F37: Pune | G37: 1
F38: Grand Total | G38: 15
F47: Row Labels | G47: Sum of amount
F48: Cash | G48: 6900
F49: Credit Card | G49: 274800
F50: Debit Card | G50: 21100
F51: UPI | G51: 150100
F52: Grand Total | G52: 452900
